tile_match_gym/__init__.py
tile_match_gym/board.py
tile_match_gym/renderer.py
tile_match_gym/tile_match_env.py
tile_match_gym/wrappers.py
tile_match_gym/utils/__init__.py
tile_match_gym/utils/print_board_diffs.py
tile_match_gym/utils/utils.py
tile_match_gym-1.0.6.dist-info/LICENSE
tile_match_gym-1.0.6.dist-info/METADATA
tile_match_gym-1.0.6.dist-info/WHEEL
tile_match_gym-1.0.6.dist-info/top_level.txt
tile_match_gym-1.0.6.dist-info/RECORD
