Metadata-Version: 2.1
Name: tile-match-gym
Version: 1.0.6
Summary: A set of reinforcement learning environments for tile matching games, consistent with the OpenAI Gymnasium API.
Author: James Elson
Author-email: Akshil Patel <akshilpatel11@gmail.com>
License: Copyright (c) 2023, Akshil Patel
Project-URL: Homepage, https://github.com/akshilpatel/tile-match-gym
Project-URL: Issues, https://github.com/akshilpatel/tile-match-gym/issues
Keywords: reinforcement-learning,gym,tile-matching,games,rl,openai-gym,gymnasium,rl-environment
Classifier: Intended Audience :: Science/Research
Classifier: License :: OSI Approved :: BSD License
Classifier: Programming Language :: Python :: 3
Classifier: Programming Language :: Python :: 3.8
Classifier: Programming Language :: Python :: 3.9
Classifier: Programming Language :: Python :: 3.10
Classifier: Programming Language :: Python :: 3.11
Classifier: Programming Language :: Python :: 3.12
Classifier: Topic :: Scientific/Engineering :: Artificial Intelligence
Requires-Python: >=3.8
License-File: LICENSE
Requires-Dist: numpy>=1.24.3
Requires-Dist: gymnasium>=1.0.0
Requires-Dist: numba==0.59.1
Requires-Dist: pygame==2.6.1
Provides-Extra: testing
Requires-Dist: pytest>=7.4.0; extra == "testing"
